onetimesecret/__init__.py
onetimesecret/onetimesecret.py
onetimesecret-1.dist-info/LICENSE
onetimesecret-1.dist-info/METADATA
onetimesecret-1.dist-info/WHEEL
onetimesecret-1.dist-info/RECORD
