Metadata-Version: 2.1
Name: onetimesecret
Version: 1
Summary: simple api client for onetimesecret.com
License: Apache Software License
Author: Mauricio
Author-email: mtdb.github.n20n0@passinbox.com
Requires-Python: >=3.10,<4.0
Classifier: License :: OSI Approved :: Apache Software License
Classifier: License :: Other/Proprietary License
Classifier: Operating System :: OS Independent
Classifier: Programming Language :: Python :: 3
Classifier: Programming Language :: Python :: 3.10
Classifier: Programming Language :: Python :: 3.11
Classifier: Programming Language :: Python :: 3.12
Requires-Dist: requests (>=2.32.3,<3.0.0)
